markdown_alerts.py
markdown_alerts-0.1.dist-info/LICENSE
markdown_alerts-0.1.dist-info/METADATA
markdown_alerts-0.1.dist-info/WHEEL
markdown_alerts-0.1.dist-info/top_level.txt
markdown_alerts-0.1.dist-info/RECORD
