Metadata-Version: 2.1
Name: markdown-alerts
Version: 0.1
Summary: Python-Markdown Admonition alternative.
Home-page: https://gitea.gch.icu/gd/markdown-alerts/
Author: gd
License: UNKNOWN
Platform: UNKNOWN
Classifier: Programming Language :: Python :: 3.9
Classifier: License :: OSI Approved :: The Unlicense (Unlicense)
Classifier: Operating System :: OS Independent
Requires-Python: >=3.6
Requires-Dist: markdown (>=3.0)
